tenduke_scale/__init__.py
tenduke_scale/auth/__init__.py
tenduke_scale/auth/scale_jwt_auth_provider.py
tenduke_scale/describe_license_options.py
tenduke_scale/exceptions/__init__.py
tenduke_scale/exceptions/validation.py
tenduke_scale/http/__init__.py
tenduke_scale/http/scale_session_factory.py
tenduke_scale/license_checkout/__init__.py
tenduke_scale/license_checkout/client_details.py
tenduke_scale/license_checkout/enforced_license_checkout_client.py
tenduke_scale/license_checkout/feature_flags_response.py
tenduke_scale/license_checkout/feature_flags_token.py
tenduke_scale/license_checkout/jwk_provider.py
tenduke_scale/license_checkout/license_checkout_arguments.py
tenduke_scale/license_checkout/license_checkout_client.py
tenduke_scale/license_checkout/license_consumer_client_binding_status.py
tenduke_scale/license_checkout/license_consumer_licenses_status.py
tenduke_scale/license_checkout/license_consumption_client_binding.py
tenduke_scale/license_checkout/license_heartbeat_arguments.py
tenduke_scale/license_checkout/license_release_arguments.py
tenduke_scale/license_checkout/license_release_result.py
tenduke_scale/license_checkout/license_token.py
tenduke_scale/license_checkout/metered_license_checkout_client.py
tenduke_scale/license_checkout/token_store.py
tenduke_scale/license_checkout/verification_key_store.py
tenduke_scale/licensing/__init__.py
tenduke_scale/licensing/consumer_type.py
tenduke_scale/licensing/effective_product_config_info.py
tenduke_scale/licensing/license.py
tenduke_scale/licensing/license_consumer.py
tenduke_scale/licensing/license_container.py
tenduke_scale/licensing/license_feature.py
tenduke_scale/licensing/license_key.py
tenduke_scale/licensing/license_metadata.py
tenduke_scale/licensing/license_model.py
tenduke_scale/licensing/quantity_dimension.py
tenduke_scale/licensing/quantity_enforcement_type.py
tenduke_scale/paging.py
tenduke_scale/py.typed
tenduke_scale-2.3.0.dist-info/LICENSE
tenduke_scale-2.3.0.dist-info/METADATA
tenduke_scale-2.3.0.dist-info/WHEEL
tenduke_scale-2.3.0.dist-info/RECORD
