Metadata-Version: 2.3
Name: tenduke_scale
Version: 2.3.0
Summary: API client for 10Duke Scale.
License: MIT
Requires-Python: >=3.10,<4.0
Classifier: Development Status :: 5 - Production/Stable
Classifier: Environment :: Console
Classifier: Environment :: Web Environment
Classifier: Intended Audience :: Developers
Classifier: License :: OSI Approved :: MIT License
Classifier: Natural Language :: English
Classifier: Operating System :: OS Independent
Classifier: Programming Language :: Python
Classifier: Programming Language :: Python :: 3
Classifier: Programming Language :: Python :: 3.10
Classifier: Programming Language :: Python :: 3.11
Classifier: Programming Language :: Python :: 3.12
Classifier: Programming Language :: Python :: 3.13
Classifier: Programming Language :: Python :: 3 :: Only
Classifier: Topic :: Software Development
Classifier: Typing :: Typed
Requires-Dist: platformdirs (>=4.3.8,<5.0.0)
Requires-Dist: pyjwt (>=2.10.1,<3.0.0)
Requires-Dist: requests[security] (>=2.32.3,<3.0.0)
Requires-Dist: tenduke-core (==3.0.1)
Project-URL: Repository, https://gitlab.com/10Duke/scale/python/python-scale-sdk
